nonebot_plugin_helldivers_tools/__init__.py
nonebot_plugin_helldivers_tools/data/equipment.json
nonebot_plugin_helldivers_tools/data/font/msyh.ttc
nonebot_plugin_helldivers_tools/data/plantes_mix.json
nonebot_plugin_helldivers_tools/img/helldivers/A-FLAM-40 火焰喷射哨戒炮.png
nonebot_plugin_helldivers_tools/img/helldivers/A-G-16 加特林哨戒炮.png
nonebot_plugin_helldivers_tools/img/helldivers/A-M-23 电磁冲击波迫击哨戒炮.png
nonebot_plugin_helldivers_tools/img/helldivers/A-MG-43 哨戒机枪.png
nonebot_plugin_helldivers_tools/img/helldivers/A-MLS-4X 火箭哨戒炮.png
nonebot_plugin_helldivers_tools/img/helldivers/AAC-8 自动哨戒炮.png
nonebot_plugin_helldivers_tools/img/helldivers/AARC-3 特斯拉塔.png
nonebot_plugin_helldivers_tools/img/helldivers/AC-8 机炮.png
nonebot_plugin_helldivers_tools/img/helldivers/AM-12 迫击哨戒炮.png
nonebot_plugin_helldivers_tools/img/helldivers/APW-1 反器材步枪.png
nonebot_plugin_helldivers_tools/img/helldivers/ARC-3 电弧发射器.png
nonebot_plugin_helldivers_tools/img/helldivers/AX-AR-3 护卫犬.png
nonebot_plugin_helldivers_tools/img/helldivers/AX-LAS-5 护卫犬漫游车.png
nonebot_plugin_helldivers_tools/img/helldivers/AX-TX-13 护卫犬腐息.png
nonebot_plugin_helldivers_tools/img/helldivers/B-1 补给背包.png
nonebot_plugin_helldivers_tools/img/helldivers/E-AT-12 反坦克炮台.png
nonebot_plugin_helldivers_tools/img/helldivers/E-MG-101 重机枪部署支架.png
nonebot_plugin_helldivers_tools/img/helldivers/EAT-17 消耗性反坦克武器.png
nonebot_plugin_helldivers_tools/img/helldivers/EXO-45 爱国者外骨骼装甲.png
nonebot_plugin_helldivers_tools/img/helldivers/EXO-49 解放者外骨骼装甲.png
nonebot_plugin_helldivers_tools/img/helldivers/FAF-14 飞矛.png
nonebot_plugin_helldivers_tools/img/helldivers/FLAM-40 火焰喷射器.png
nonebot_plugin_helldivers_tools/img/helldivers/FX-12 防护罩生成中继器.png
nonebot_plugin_helldivers_tools/img/helldivers/GL-21 榴弹发射器.png
nonebot_plugin_helldivers_tools/img/helldivers/GR-8 无后座力炮.png
nonebot_plugin_helldivers_tools/img/helldivers/LAS-98 激光大炮.png
nonebot_plugin_helldivers_tools/img/helldivers/LAS-99 类星体加农炮.png
nonebot_plugin_helldivers_tools-0.1.0.dist-info/LICENSE
nonebot_plugin_helldivers_tools-0.1.0.dist-info/METADATA
nonebot_plugin_helldivers_tools-0.1.0.dist-info/WHEEL
nonebot_plugin_helldivers_tools-0.1.0.dist-info/RECORD
