Metadata-Version: 2.1
Name: nonebot_plugin_helldivers_tools
Version: 0.1.0
Summary: NoneBot2 绝地潜兵助手
Home-page: https://github.com/sansenhoshi/nonebot_plugin_helldivers_tools
Keywords: nonebot2,helldivers
Author: sansenhoshi
Requires-Python: >=3.9
Classifier: Programming Language :: Python :: 3
Classifier: Programming Language :: Python :: 3.9
Classifier: Programming Language :: Python :: 3.10
Classifier: Programming Language :: Python :: 3.11
Classifier: Programming Language :: Python :: 3.12
Classifier: Programming Language :: Python :: 3.13
Requires-Dist: httpx (>=0.23.3)
Requires-Dist: nonebot-adapter-onebot (>=2.0.0,<3.0.0)
Requires-Dist: nonebot2 (>=2.2.0)
Requires-Dist: pillow (>=9.5.0)
Requires-Dist: playwright (>=1.46.0)
Project-URL: Repository, https://github.com/sansenhoshi/nonebot_plugin_helldivers_tools
